{
    "upgrades": {
        "mon-calamari-shield-techs-old-legacy": {
            "author": "Armada Legacy",
            "alias": "OldLegacy", 
            "team": "Armada Legacy",
            "release": "Legacy Wave 2 Old",
            "expansion": "Mon Remonda Expansion",
            "_id": null,
            "type": "support-team",
            "faction": [
                ""
            ],
            "name": "Mon Calamari Shield Techs",
            "unique-class": [
                ""
            ],
            "ability": "\"MC\" only.\nWhile defending, after you suffer damage, if the defending hull zone has no shields, you may discard this card to recover up to 2 shields in the defending hull zone.",
            "unique": false,
            "points": 5,
            "modification": false,
            "bound_shiptype": "",
            "restrictions": {
                "traits": [
                    "MC"
                ],
                "size": [
                    ""
                ],
                "disqual_upgrades": [
                    ""
                ],
                "disable_upgrades": [
                    ""
                ],
                "enable_upgrades": [
                    ""
                ],
                "flagship": false
            },
            "start_command": {
                "type": "",
                "start_icon": [
                    ""
                ],
                "start_amount": 0
            },
            "exhaust": {
                "type": "",
                "ready_token": [
                    ""
                ],
                "ready_amount": 0
            },
            "artwork": "",
            "cardimage": "https://api.swarmada.wiki/images/mon-calamari-shield-techs-old-legacy.webp"
        }
    }
}